gretel/__init__.py
gretel/cmd.py
gretel/gretel.py
gretel/snpper.py
gretel/util.py
tests/__init__.py
tests/test_test.py
gretel-0.0.94.dist-info/LICENSE
gretel-0.0.94.dist-info/METADATA
gretel-0.0.94.dist-info/WHEEL
gretel-0.0.94.dist-info/entry_points.txt
gretel-0.0.94.dist-info/top_level.txt
gretel-0.0.94.dist-info/RECORD
