Metadata-Version: 2.1
Name: gretel
Version: 0.0.94
Summary: An algorithm for recovering potential haplotypes from metagenomes
Home-page: https://github.com/samstudio8/gretel
Author: Sam Nicholls
Author-email: sam@samnicholls.net
Maintainer: Sam Nicholls
Maintainer-email: sam@samnicholls.net
License: UNKNOWN
Platform: UNKNOWN
Classifier: Development Status :: 2 - Pre-Alpha
Classifier: Intended Audience :: Science/Research
Classifier: Topic :: Scientific/Engineering
Classifier: Topic :: Scientific/Engineering :: Bio-Informatics
Classifier: License :: OSI Approved :: MIT License
Requires-Dist: numpy
Requires-Dist: hanselx (==0.0.92)
Requires-Dist: pysam
Requires-Dist: PyVCF
